{"nodes": [{"id": "e_ai_lumina_backend_brain_skill_runtime_runtime_pipeline_py", "label": "runtime_pipeline.py", "file_type": "code", "source_file": "backend/brain/skill_runtime/runtime_pipeline.py", "source_location": "L1"}, {"id": "e_ai_lumina_backend_brain_skill_runtime_runtime_pipeline_runtimepipeline", "label": "RuntimePipeline", "file_type": "code", "source_file": "backend/brain/skill_runtime/runtime_pipeline.py", "source_location": "L46", "_callable": true}, {"id": "iruntimepipeline", "label": "IRuntimePipeline", "file_type": "code", "source_file": "", "source_location": "", "origin_file": "E:\\AI\\LUMINA\\backend\\brain\\skill_runtime\\runtime_pipeline.py"}, {"id": "e_ai_lumina_backend_brain_skill_runtime_runtime_pipeline_runtimepipeline_init", "label": ".__init__()", "file_type": "code", "source_file": "backend/brain/skill_runtime/runtime_pipeline.py", "source_location": "L49", "_callable": true}, {"id": "iregistrydiscovery", "label": "IRegistryDiscovery", "file_type": "code", "source_file": "", "source_location": "", "origin_file": "E:\\AI\\LUMINA\\backend\\brain\\skill_runtime\\runtime_pipeline.py"}, {"id": "icapabilitymatcher", "label": "ICapabilityMatcher", "file_type": "code", "source_file": "", "source_location": "", "origin_file": "E:\\AI\\LUMINA\\backend\\brain\\skill_runtime\\runtime_pipeline.py"}, {"id": "idependencyresolver", "label": "IDependencyResolver", "file_type": "code", "source_file": "", "source_location": "", "origin_file": "E:\\AI\\LUMINA\\backend\\brain\\skill_runtime\\runtime_pipeline.py"}, {"id": "iskillsandbox", "label": "ISkillSandbox", "file_type": "code", "source_file": "", "source_location": "", "origin_file": "E:\\AI\\LUMINA\\backend\\brain\\skill_runtime\\runtime_pipeline.py"}, {"id": "iskillloader", "label": "ISkillLoader", "file_type": "code", "source_file": "", "source_location": "", "origin_file": "E:\\AI\\LUMINA\\backend\\brain\\skill_runtime\\runtime_pipeline.py"}, {"id": "icontextinjector", "label": "IContextInjector", "file_type": "code", "source_file": "", "source_location": "", "origin_file": "E:\\AI\\LUMINA\\backend\\brain\\skill_runtime\\runtime_pipeline.py"}, {"id": "iskillexecutor", "label": "ISkillExecutor", "file_type": "code", "source_file": "", "source_location": "", "origin_file": "E:\\AI\\LUMINA\\backend\\brain\\skill_runtime\\runtime_pipeline.py"}, {"id": "iexecutionobserver", "label": "IExecutionObserver", "file_type": "code", "source_file": "", "source_location": "", "origin_file": "E:\\AI\\LUMINA\\backend\\brain\\skill_runtime\\runtime_pipeline.py"}, {"id": "iexecutionrecorder", "label": "IExecutionRecorder", "file_type": "code", "source_file": "", "source_location": "", "origin_file": "E:\\AI\\LUMINA\\backend\\brain\\skill_runtime\\runtime_pipeline.py"}, {"id": "iexecutionpersistence", "label": "IExecutionPersistence", "file_type": "code", "source_file": "", "source_location": "", "origin_file": "E:\\AI\\LUMINA\\backend\\brain\\skill_runtime\\runtime_pipeline.py"}, {"id": "e_ai_lumina_backend_brain_skill_runtime_runtime_pipeline_runtimepipeline_run", "label": ".run()", "file_type": "code", "source_file": "backend/brain/skill_runtime/runtime_pipeline.py", "source_location": "L73", "_callable": true}, {"id": "capabilityrequest", "label": "CapabilityRequest", "file_type": "code", "source_file": "", "source_location": "", "origin_file": "E:\\AI\\LUMINA\\backend\\brain\\skill_runtime\\runtime_pipeline.py"}, {"id": "sandboxpolicy", "label": "SandboxPolicy", "file_type": "code", "source_file": "", "source_location": "", "origin_file": "E:\\AI\\LUMINA\\backend\\brain\\skill_runtime\\runtime_pipeline.py"}, {"id": "runtimepipelineresult", "label": "RuntimePipelineResult", "file_type": "code", "source_file": "", "source_location": "", "origin_file": "E:\\AI\\LUMINA\\backend\\brain\\skill_runtime\\runtime_pipeline.py"}, {"id": "e_ai_lumina_backend_brain_skill_runtime_runtime_pipeline_rationale_1", "label": "brain/skill_runtime/runtime_pipeline.py \u2014 Phase 8.11: Runtime Pipeline Orchestra", "file_type": "rationale", "source_file": "backend/brain/skill_runtime/runtime_pipeline.py", "source_location": "L1"}, {"id": "e_ai_lumina_backend_brain_skill_runtime_runtime_pipeline_rationale_47", "label": "Coordinator over the ten runtime stages. Holds no business logic.", "file_type": "rationale", "source_file": "backend/brain/skill_runtime/runtime_pipeline.py", "source_location": "L47"}], "edges": [{"source": "e_ai_lumina_backend_brain_skill_runtime_runtime_pipeline_py", "target": "typing", "relation": "imports_from", "context": "import", "confidence": "EXTRACTED", "source_file": "backend/brain/skill_runtime/runtime_pipeline.py", "source_location": "L24", "weight": 1.0}, {"source": "e_ai_lumina_backend_brain_skill_runtime_runtime_pipeline_py", "target": "brain_skill_runtime_interfaces", "relation": "imports_from", "context": "import", "confidence": "EXTRACTED", "source_file": "backend/brain/skill_runtime/runtime_pipeline.py", "source_location": "L26", "weight": 1.0}, {"source": "e_ai_lumina_backend_brain_skill_runtime_runtime_pipeline_py", "target": "brain_skill_runtime_models", "relation": "imports_from", "context": "import", "confidence": "EXTRACTED", "source_file": "backend/brain/skill_runtime/runtime_pipeline.py", "source_location": "L39", "weight": 1.0}, {"source": "e_ai_lumina_backend_brain_skill_runtime_runtime_pipeline_py", "target": "e_ai_lumina_backend_brain_skill_runtime_runtime_pipeline_runtimepipeline", "relation": "contains", "confidence": "EXTRACTED", "source_file": "backend/brain/skill_runtime/runtime_pipeline.py", "source_location": "L46", "weight": 1.0}, {"source": "e_ai_lumina_backend_brain_skill_runtime_runtime_pipeline_runtimepipeline", "target": "iruntimepipeline", "relation": "inherits", "confidence": "EXTRACTED", "source_file": "backend/brain/skill_runtime/runtime_pipeline.py", "source_location": "L46", "weight": 1.0}, {"source": "e_ai_lumina_backend_brain_skill_runtime_runtime_pipeline_runtimepipeline", "target": "e_ai_lumina_backend_brain_skill_runtime_runtime_pipeline_runtimepipeline_init", "relation": "method", "confidence": "EXTRACTED", "source_file": "backend/brain/skill_runtime/runtime_pipeline.py", "source_location": "L49", "weight": 1.0}, {"source": "e_ai_lumina_backend_brain_skill_runtime_runtime_pipeline_runtimepipeline_init", "target": "iregistrydiscovery", "relation": "references", "context": "parameter_type", "confidence": "EXTRACTED", "source_file": "backend/brain/skill_runtime/runtime_pipeline.py", "source_location": "L49", "weight": 1.0}, {"source": "e_ai_lumina_backend_brain_skill_runtime_runtime_pipeline_runtimepipeline_init", "target": "icapabilitymatcher", "relation": "references", "context": "parameter_type", "confidence": "EXTRACTED", "source_file": "backend/brain/skill_runtime/runtime_pipeline.py", "source_location": "L49", "weight": 1.0}, {"source": "e_ai_lumina_backend_brain_skill_runtime_runtime_pipeline_runtimepipeline_init", "target": "idependencyresolver", "relation": "references", "context": "parameter_type", "confidence": "EXTRACTED", "source_file": "backend/brain/skill_runtime/runtime_pipeline.py", "source_location": "L49", "weight": 1.0}, {"source": "e_ai_lumina_backend_brain_skill_runtime_runtime_pipeline_runtimepipeline_init", "target": "iskillsandbox", "relation": "references", "context": "parameter_type", "confidence": "EXTRACTED", "source_file": "backend/brain/skill_runtime/runtime_pipeline.py", "source_location": "L49", "weight": 1.0}, {"source": "e_ai_lumina_backend_brain_skill_runtime_runtime_pipeline_runtimepipeline_init", "target": "iskillloader", "relation": "references", "context": "parameter_type", "confidence": "EXTRACTED", "source_file": "backend/brain/skill_runtime/runtime_pipeline.py", "source_location": "L49", "weight": 1.0}, {"source": "e_ai_lumina_backend_brain_skill_runtime_runtime_pipeline_runtimepipeline_init", "target": "icontextinjector", "relation": "references", "context": "parameter_type", "confidence": "EXTRACTED", "source_file": "backend/brain/skill_runtime/runtime_pipeline.py", "source_location": "L49", "weight": 1.0}, {"source": "e_ai_lumina_backend_brain_skill_runtime_runtime_pipeline_runtimepipeline_init", "target": "iskillexecutor", "relation": "references", "context": "parameter_type", "confidence": "EXTRACTED", "source_file": "backend/brain/skill_runtime/runtime_pipeline.py", "source_location": "L49", "weight": 1.0}, {"source": "e_ai_lumina_backend_brain_skill_runtime_runtime_pipeline_runtimepipeline_init", "target": "iexecutionobserver", "relation": "references", "context": "parameter_type", "confidence": "EXTRACTED", "source_file": "backend/brain/skill_runtime/runtime_pipeline.py", "source_location": "L49", "weight": 1.0}, {"source": "e_ai_lumina_backend_brain_skill_runtime_runtime_pipeline_runtimepipeline_init", "target": "iexecutionrecorder", "relation": "references", "context": "parameter_type", "confidence": "EXTRACTED", "source_file": "backend/brain/skill_runtime/runtime_pipeline.py", "source_location": "L49", "weight": 1.0}, {"source": "e_ai_lumina_backend_brain_skill_runtime_runtime_pipeline_runtimepipeline_init", "target": "iexecutionpersistence", "relation": "references", "context": "parameter_type", "confidence": "EXTRACTED", "source_file": "backend/brain/skill_runtime/runtime_pipeline.py", "source_location": "L49", "weight": 1.0}, {"source": "e_ai_lumina_backend_brain_skill_runtime_runtime_pipeline_runtimepipeline", "target": "e_ai_lumina_backend_brain_skill_runtime_runtime_pipeline_runtimepipeline_run", "relation": "method", "confidence": "EXTRACTED", "source_file": "backend/brain/skill_runtime/runtime_pipeline.py", "source_location": "L73", "weight": 1.0}, {"source": "e_ai_lumina_backend_brain_skill_runtime_runtime_pipeline_runtimepipeline_run", "target": "capabilityrequest", "relation": "references", "context": "parameter_type", "confidence": "EXTRACTED", "source_file": "backend/brain/skill_runtime/runtime_pipeline.py", "source_location": "L73", "weight": 1.0}, {"source": "e_ai_lumina_backend_brain_skill_runtime_runtime_pipeline_runtimepipeline_run", "target": "sandboxpolicy", "relation": "references", "context": "parameter_type", "confidence": "EXTRACTED", "source_file": "backend/brain/skill_runtime/runtime_pipeline.py", "source_location": "L73", "weight": 1.0}, {"source": "e_ai_lumina_backend_brain_skill_runtime_runtime_pipeline_runtimepipeline_run", "target": "runtimepipelineresult", "relation": "references", "context": "return_type", "confidence": "EXTRACTED", "source_file": "backend/brain/skill_runtime/runtime_pipeline.py", "source_location": "L73", "weight": 1.0}, {"source": "e_ai_lumina_backend_brain_skill_runtime_runtime_pipeline_runtimepipeline_run", "target": "runtimepipelineresult", "relation": "calls", "context": "call", "confidence": "EXTRACTED", "source_file": "backend/brain/skill_runtime/runtime_pipeline.py", "source_location": "L96", "weight": 1.0}, {"source": "e_ai_lumina_backend_brain_skill_runtime_runtime_pipeline_rationale_1", "target": "e_ai_lumina_backend_brain_skill_runtime_runtime_pipeline_py", "relation": "rationale_for", "confidence": "EXTRACTED", "source_file": "backend/brain/skill_runtime/runtime_pipeline.py", "source_location": "L1", "weight": 1.0}, {"source": "e_ai_lumina_backend_brain_skill_runtime_runtime_pipeline_rationale_47", "target": "e_ai_lumina_backend_brain_skill_runtime_runtime_pipeline_runtimepipeline", "relation": "rationale_for", "confidence": "EXTRACTED", "source_file": "backend/brain/skill_runtime/runtime_pipeline.py", "source_location": "L47", "weight": 1.0}], "raw_calls": [{"caller_nid": "e_ai_lumina_backend_brain_skill_runtime_runtime_pipeline_runtimepipeline_run", "callee": "discover", "is_member_call": true, "source_file": "backend/brain/skill_runtime/runtime_pipeline.py", "source_location": "L94", "receiver": null}, {"caller_nid": "e_ai_lumina_backend_brain_skill_runtime_runtime_pipeline_runtimepipeline_run", "callee": "match", "is_member_call": true, "source_file": "backend/brain/skill_runtime/runtime_pipeline.py", "source_location": "L99", "receiver": null}, {"caller_nid": "e_ai_lumina_backend_brain_skill_runtime_runtime_pipeline_runtimepipeline_run", "callee": "resolve", "is_member_call": true, "source_file": "backend/brain/skill_runtime/runtime_pipeline.py", "source_location": "L106", "receiver": null}, {"caller_nid": "e_ai_lumina_backend_brain_skill_runtime_runtime_pipeline_runtimepipeline_run", "callee": "evaluate", "is_member_call": true, "source_file": "backend/brain/skill_runtime/runtime_pipeline.py", "source_location": "L119", "receiver": null}, {"caller_nid": "e_ai_lumina_backend_brain_skill_runtime_runtime_pipeline_runtimepipeline_run", "callee": "load", "is_member_call": true, "source_file": "backend/brain/skill_runtime/runtime_pipeline.py", "source_location": "L129", "receiver": null}, {"caller_nid": "e_ai_lumina_backend_brain_skill_runtime_runtime_pipeline_runtimepipeline_run", "callee": "inject", "is_member_call": true, "source_file": "backend/brain/skill_runtime/runtime_pipeline.py", "source_location": "L138", "receiver": null}, {"caller_nid": "e_ai_lumina_backend_brain_skill_runtime_runtime_pipeline_runtimepipeline_run", "callee": "execute", "is_member_call": true, "source_file": "backend/brain/skill_runtime/runtime_pipeline.py", "source_location": "L157", "receiver": null}, {"caller_nid": "e_ai_lumina_backend_brain_skill_runtime_runtime_pipeline_runtimepipeline_run", "callee": "observe", "is_member_call": true, "source_file": "backend/brain/skill_runtime/runtime_pipeline.py", "source_location": "L159", "receiver": null}, {"caller_nid": "e_ai_lumina_backend_brain_skill_runtime_runtime_pipeline_runtimepipeline_run", "callee": "record", "is_member_call": true, "source_file": "backend/brain/skill_runtime/runtime_pipeline.py", "source_location": "L160", "receiver": null}, {"caller_nid": "e_ai_lumina_backend_brain_skill_runtime_runtime_pipeline_runtimepipeline_run", "callee": "prepare", "is_member_call": true, "source_file": "backend/brain/skill_runtime/runtime_pipeline.py", "source_location": "L164", "receiver": null}, {"caller_nid": "e_ai_lumina_backend_brain_skill_runtime_runtime_pipeline_runtimepipeline_run", "callee": "observe", "is_member_call": true, "source_file": "backend/brain/skill_runtime/runtime_pipeline.py", "source_location": "L173", "receiver": null}, {"caller_nid": "e_ai_lumina_backend_brain_skill_runtime_runtime_pipeline_runtimepipeline_run", "callee": "record", "is_member_call": true, "source_file": "backend/brain/skill_runtime/runtime_pipeline.py", "source_location": "L174", "receiver": null}, {"caller_nid": "e_ai_lumina_backend_brain_skill_runtime_runtime_pipeline_runtimepipeline_run", "callee": "prepare", "is_member_call": true, "source_file": "backend/brain/skill_runtime/runtime_pipeline.py", "source_location": "L178", "receiver": null}]}